jira_oauth_generator/access_using_jira_library.py
jira_oauth_generator/access_using_requests_package.py
jira_oauth_generator/jira_oauth_token_generator.py
jira_oauth_generator-0.1.7.dist-info/WHEEL
jira_oauth_generator-0.1.7.dist-info/METADATA
jira_oauth_generator-0.1.7.dist-info/RECORD
