Metadata-Version: 2.1
Name: jira-oauth-generator
Version: 0.1.7
Summary: Generator of access token for Jira OAuth
Home-page: https://github.com/rominf/jira-oauth-generator
License: Apache-2.0
Author: Raju Kadam
Requires-Python: >=3.5,<4.0
Classifier: License :: OSI Approved :: Apache Software License
Classifier: Programming Language :: Python :: 3
Classifier: Programming Language :: Python :: 3.5
Classifier: Programming Language :: Python :: 3.6
Classifier: Programming Language :: Python :: 3.7
Requires-Dist: PyJWT (>=1.7,<2.0)
Requires-Dist: asn1crypto (>=0.24.0,<0.25.0)
Requires-Dist: certifi (>=2018.11,<2019.0)
Requires-Dist: cffi (>=1.11,<2.0)
Requires-Dist: chardet (>=3.0,<4.0)
Requires-Dist: click (>=7.0,<8.0)
Requires-Dist: cryptography (>=2.4,<3.0)
Requires-Dist: defusedxml (>=0.5.0,<0.6.0)
Requires-Dist: httplib2 (>=0.12.0,<0.13.0)
Requires-Dist: idna (>=2.8,<3.0)
Requires-Dist: jira (>=2.0,<3.0)
Requires-Dist: oauth2 (>=1.9,<2.0)
Requires-Dist: oauthlib (>=2.1,<3.0)
Requires-Dist: pbr (>=5.1,<6.0)
Requires-Dist: pycparser (>=2.19,<3.0)
Requires-Dist: requests (>=2.15.1,<3.0.0)
Requires-Dist: requests-oauthlib (>=1.0.0,<2.0.0)
Requires-Dist: requests-toolbelt (>=0.8.0,<0.9.0)
Requires-Dist: six (>=1.11,<2.0)
Requires-Dist: tlslite (>=0.4.9,<0.5.0)
Requires-Dist: urllib3 (>=1.24,<2.0)
Project-URL: Repository, https://github.com/rominf/jira-oauth-generator
